etna/__init__.py
etna/analysis/__init__.py
etna/analysis/eda_utils.py
etna/analysis/feature_relevance/__init__.py
etna/analysis/feature_relevance/relevance.py
etna/analysis/feature_relevance/relevance_table.py
etna/analysis/outliers/__init__.py
etna/analysis/outliers/confidence_interval_outliers.py
etna/analysis/outliers/density_outliers.py
etna/analysis/outliers/hist_outliers.py
etna/analysis/outliers/median_outliers.py
etna/analysis/outliers/sequence_outliers.py
etna/analysis/plotters.py
etna/clustering/__init__.py
etna/clustering/base.py
etna/clustering/distances/__init__.py
etna/clustering/distances/base.py
etna/clustering/distances/distance_matrix.py
etna/clustering/distances/dtw_distance.py
etna/clustering/distances/euclidean_distance.py
etna/clustering/hierarchical/__init__.py
etna/clustering/hierarchical/base.py
etna/clustering/hierarchical/dtw_clustering.py
etna/clustering/hierarchical/euclidean_clustering.py
etna/commands/__init__.py
etna/commands/__main__.py
etna/commands/backtest_command.py
etna/commands/forecast_command.py
etna/commands/resolvers.py
etna/core/__init__.py
etna/core/mixins.py
etna/datasets/__init__.py
etna/datasets/datasets_generation.py
etna/datasets/tsdataset.py
etna/ensembles/__init__.py
etna/ensembles/stacking_ensemble.py
etna/ensembles/voting_ensemble.py
etna/libs/tsfresh/__init__.py
etna/libs/tsfresh/defaults.py
etna/libs/tsfresh/distribution.py
etna/libs/tsfresh/relevance.py
etna/libs/tsfresh/significance_tests.py
etna/loggers/__init__.py
etna/loggers/base.py
etna/loggers/console_logger.py
etna/loggers/wandb_logger.py
etna/metrics/__init__.py
etna/metrics/base.py
etna/metrics/functional_metrics.py
etna/metrics/metrics.py
etna/metrics/utils.py
etna/model_selection/__init__.py
etna/model_selection/backtest.py
etna/models/__init__.py
etna/models/base.py
etna/models/catboost.py
etna/models/linear.py
etna/models/moving_average.py
etna/models/naive.py
etna/models/nn/__init__.py
etna/models/nn/deepar.py
etna/models/nn/tft.py
etna_ts-1.3.1.dist-info/entry_points.txt
etna_ts-1.3.1.dist-info/LICENSE
etna_ts-1.3.1.dist-info/WHEEL
etna_ts-1.3.1.dist-info/METADATA
etna_ts-1.3.1.dist-info/RECORD
